anonlink/__init__.py
anonlink/_deprecation.py
anonlink/benchmark.py
anonlink/blocking.py
anonlink/candidate_generation.py
anonlink/concurrency.py
anonlink/serialization.py
anonlink/stats.py
anonlink/typechecking.py
anonlink/similarities/__init__.py
anonlink/similarities/_dice.pypy37-pp73-win_amd64.pyd
anonlink/similarities/_dice_python.py
anonlink/similarities/_dice_x86.py
anonlink/similarities/_smc.py
anonlink/similarities/_utils.py
anonlink/solving/__init__.py
anonlink/solving/_multiparty_solving.pypy37-pp73-win_amd64.pyd
anonlink/solving/_multiparty_solving_python.py
anonlink-0.15.3.dist-info/LICENSE
anonlink-0.15.3.dist-info/METADATA
anonlink-0.15.3.dist-info/WHEEL
anonlink-0.15.3.dist-info/top_level.txt
anonlink-0.15.3.dist-info/RECORD
